flextruct/__init__.py
flextruct/nominal_structure.py
flextruct/pygraph_tools.py
flextruct-1.0.2.dist-info/METADATA
flextruct-1.0.2.dist-info/WHEEL
flextruct-1.0.2.dist-info/top_level.txt
flextruct-1.0.2.dist-info/RECORD
